[{"name":"rkpm_cpu_np_1_peak_memory","value_last":6098.69140625,"value_new":6095.8828125,"unit":"MB","percent_difference":-0.0460523998,"absolute_difference":-2.80859375,"percent_total_difference":-0.1445717123,"performance_quality":0.1445717123},{"name":"rkpm_cpu_np_4_peak_memory","value_last":5729.3828125,"value_new":5720.28515625,"unit":"MB","percent_difference":-0.1587894639,"absolute_difference":-9.09765625,"percent_total_difference":-0.4682997468,"performance_quality":0.4682997468},{"name":"rkpm_gpu_np_1_peak_memory","value_last":5300.09375,"value_new":5298.30078125,"unit":"MB","percent_difference":-0.0338290007,"absolute_difference":-1.79296875,"percent_total_difference":-0.0922926508,"performance_quality":0.0922926508},{"name":"fem_strain_smoothing_cpu_np_1_peak_memory","value_last":5980.80859375,"value_new":5969.3515625,"unit":"MB","percent_difference":-0.1915632489,"absolute_difference":-11.45703125,"percent_total_difference":-0.589748028,"performance_quality":0.589748028},{"name":"fem_strain_smoothing_gpu_np_1_peak_memory","value_last":4960.31640625,"value_new":4953.5703125,"unit":"MB","percent_difference":-0.1360012789,"absolute_difference":-6.74609375,"percent_total_difference":-0.3472536121,"performance_quality":0.3472536121},{"name":"fem_strain_smoothing_cpu_np_4_peak_memory","value_last":5330.94921875,"value_new":5408.08984375,"unit":"MB","percent_difference":1.4470335738,"absolute_difference":77.140625,"percent_total_difference":3.9707957919,"performance_quality":-3.9707957919},{"name":"fem_cpu_np_4_peak_memory","value_last":2980.7578125,"value_new":2922.38671875,"unit":"MB","percent_difference":-1.9582635498,"absolute_difference":-58.37109375,"percent_total_difference":-3.0046385213,"performance_quality":3.0046385213},{"name":"fem_cpu_np_1_peak_memory","value_last":3570.20703125,"value_new":3566.8515625,"unit":"MB","percent_difference":-0.0939852709,"absolute_difference":-3.35546875,"percent_total_difference":-0.1727219762,"performance_quality":0.1727219762},{"name":"fem_gpu_np_1_peak_memory","value_last":3501.90234375,"value_new":3490.421875,"unit":"MB","percent_difference":-0.3278352056,"absolute_difference":-11.48046875,"percent_total_difference":-0.5909544679,"performance_quality":0.5909544679},{"name":"rkpm_fbar_cpu_np_4_peak_memory","value_last":20740.8046875,"value_new":20956.16015625,"unit":"MB","percent_difference":1.0383178088,"absolute_difference":215.35546875,"percent_total_difference":11.0853728378,"performance_quality":-11.0853728378},{"name":"rkpm_fbar_cpu_np_1_peak_memory","value_last":22269.015625,"value_new":22253.5546875,"unit":"MB","percent_difference":-0.0694280239,"absolute_difference":-15.4609375,"percent_total_difference":-0.7958481742,"performance_quality":0.7958481742},{"name":"rkpm_fbar_gpu_np_1_peak_memory","value_last":17564.79296875,"value_new":17638.5859375,"unit":"MB","percent_difference":0.4201186366,"absolute_difference":73.79296875,"percent_total_difference":3.7984759623,"performance_quality":-3.7984759623},{"name":"rkpm_nodal_cpu_np_1_peak_memory","value_last":8366.02734375,"value_new":8366.421875,"unit":"MB","percent_difference":0.0047158733,"absolute_difference":0.39453125,"percent_total_difference":0.0203084046,"performance_quality":-0.0203084046},{"name":"rkpm_nodal_gpu_np_1_peak_memory","value_last":8384.8671875,"value_new":8370.203125,"unit":"MB","percent_difference":-0.1748872364,"absolute_difference":-14.6640625,"percent_total_difference":-0.7548292183,"performance_quality":0.7548292183},{"name":"rkpm_nodal_cpu_np_4_peak_memory","value_last":9204.6796875,"value_new":9178.125,"unit":"MB","percent_difference":-0.2884911632,"absolute_difference":-26.5546875,"percent_total_difference":-1.3668963841,"performance_quality":1.3668963841}]